tandoorinights/__init__.py
tandoorinights/add.py
tandoorinights/subtract.py
tandoorinights/extras/__init__.py
tandoorinights/extras/divide.py
tandoorinights/extras/multiply.py
tandoorinights-0.0.8.dist-info/METADATA
tandoorinights-0.0.8.dist-info/WHEEL
tandoorinights-0.0.8.dist-info/top_level.txt
tandoorinights-0.0.8.dist-info/RECORD
